pdfgpt/__init__.py
pdfgpt/__main__.py
pdfgpt/pdfgpt.py
pdfgptlib-0.1.0.dist-info/LICENSE
pdfgptlib-0.1.0.dist-info/METADATA
pdfgptlib-0.1.0.dist-info/WHEEL
pdfgptlib-0.1.0.dist-info/entry_points.txt
pdfgptlib-0.1.0.dist-info/top_level.txt
pdfgptlib-0.1.0.dist-info/RECORD
