Metadata-Version: 2.1
Name: pdfgptlib
Version: 0.1.0
Summary: Extract PDF contents with the magic of GPT.
Author-email: DaYuan Tan <dr.dayuantan@gmail.com>
License: Apache License
Project-URL: Homepage, https://github.com/DayuanTan/pdfgptlib
Project-URL: Repository, https://github.com/DayuanTan/pdfgptlib
Keywords: pdf,gpt,llm
Classifier: License :: OSI Approved :: Apache Software License
Classifier: Programming Language :: Python
Classifier: Programming Language :: Python :: 3
Classifier: Natural Language :: English
Classifier: Topic :: Scientific/Engineering :: Artificial Intelligence
Requires-Python: >=3
License-File: LICENSE
Requires-Dist: openai
Requires-Dist: pydantic
Requires-Dist: pymupdf
Provides-Extra: build
Requires-Dist: build; extra == "build"
Requires-Dist: twine; extra == "build"
Provides-Extra: dev
Requires-Dist: pip-tools; extra == "dev"
Requires-Dist: pytest; extra == "dev"
